imgshape/__init__.py
imgshape/__main__.py
imgshape/analyze.py
imgshape/artifacts_v4.py
imgshape/atlas.py
imgshape/augmentations.py
imgshape/cli.py
imgshape/compatibility.py
imgshape/decision_v4.py
imgshape/fingerprint_v4.py
imgshape/migrate_v2_to_v3.py
imgshape/pipeline.py
imgshape/recommender.py
imgshape/report.py
imgshape/resize.py
imgshape/server.py
imgshape/shape.py
imgshape/torchloader.py
imgshape/validator_v4.py
imgshape/version.py
imgshape/viz.py
imgshape/plugins/__init__.py
imgshape/plugins/sample_plugin.py
imgshape/profiles/edge.yaml
imgshape/profiles/medical.yaml
imgshape/profiles/ocr.yaml
imgshape/profiles/satellite.yaml
imgshape/schemas/plugin_schema.py
imgshape-4.0.0.dist-info/licenses/LICENSE
imgshape-4.0.0.dist-info/METADATA
imgshape-4.0.0.dist-info/WHEEL
imgshape-4.0.0.dist-info/entry_points.txt
imgshape-4.0.0.dist-info/top_level.txt
imgshape-4.0.0.dist-info/RECORD
