Metadata-Version: 2.4
Name: imgshape
Version: 4.0.0
Summary: imgshape v4.0.0 (Atlas) — Dataset intelligence layer: deterministic fingerprinting and decision-making for ML pipelines.
Home-page: https://github.com/STiFLeR7/imgshape
Author: Stifler
Author-email: Stifler <hillaniljppatel@gmail.com>
License: MIT
Project-URL: Homepage, https://github.com/STiFLeR7/imgshape
Project-URL: Source, https://github.com/STiFLeR7/imgshape
Project-URL: Issues, https://github.com/STiFLeR7/imgshape/issues
Project-URL: Documentation, https://stifler7.github.io/imgshape/
Requires-Python: >=3.8
License-File: LICENSE
Requires-Dist: Pillow>=9.0.0
Requires-Dist: numpy>=1.21.0
Requires-Dist: matplotlib>=3.4.0
Requires-Dist: scikit-image>=0.19.0
Requires-Dist: fastapi>=0.104.0
Requires-Dist: uvicorn[standard]>=0.24.0
Requires-Dist: pyyaml>=6.0
Requires-Dist: requests>=2.28.0
Provides-Extra: torch
Requires-Dist: torch>=1.12.0; (platform_system != "Windows" or python_version >= "3.8") and extra == "torch"
Requires-Dist: torchvision>=0.13.0; extra == "torch"
Provides-Extra: pdf
Requires-Dist: weasyprint>=53.0; extra == "pdf"
Requires-Dist: reportlab>=3.6.0; extra == "pdf"
Requires-Dist: pyyaml>=6.0; extra == "pdf"
Provides-Extra: viz
Requires-Dist: plotly>=5.20.0; extra == "viz"
Requires-Dist: seaborn>=0.12.0; extra == "viz"
Provides-Extra: web
Requires-Dist: fastapi>=0.104.0; extra == "web"
Requires-Dist: uvicorn[standard]>=0.24.0; extra == "web"
Requires-Dist: jinja2>=3.1.0; extra == "web"
Provides-Extra: plugins
Requires-Dist: importlib-metadata>=6.0; extra == "plugins"
Provides-Extra: dev
Requires-Dist: pytest>=7.0; extra == "dev"
Requires-Dist: black>=23.0; extra == "dev"
Requires-Dist: flake8>=3.9; extra == "dev"
Requires-Dist: pre-commit>=2.20; extra == "dev"
Requires-Dist: mypy>=1.0; extra == "dev"
Requires-Dist: build>=1.2; extra == "dev"
Requires-Dist: twine>=4.0; extra == "dev"
Provides-Extra: full
Requires-Dist: torch>=1.12.0; extra == "full"
Requires-Dist: torchvision>=0.13.0; extra == "full"
Requires-Dist: weasyprint>=53.0; extra == "full"
Requires-Dist: reportlab>=3.6.0; extra == "full"
Requires-Dist: pyyaml>=6.0; extra == "full"
Requires-Dist: plotly>=5.20.0; extra == "full"
Requires-Dist: seaborn>=0.12.0; extra == "full"
Requires-Dist: fastapi>=0.104.0; extra == "full"
Requires-Dist: uvicorn[standard]>=0.24.0; extra == "full"
Requires-Dist: jinja2>=3.1.0; extra == "full"
Dynamic: author
Dynamic: home-page
Dynamic: license-file
Dynamic: requires-python
